[
    {
        "gruppo": "1",
        "icona": "C:/Users/samsung/Desktop/PAO grafica/untitled/img/aria.png",
        "id": 0,
        "nome": "Qualità aria",
        "sogliaMassima": 180,
        "tipo": "SensoreAria",
        "unitaMisura": "IQA",
        "valore": 70.32
    },
    {
        "gruppo": "TempTarget 20",
        "icona": "C:/Users/samsung/Desktop/PAO grafica/untitled/img/termometro.png",
        "id": 1,
        "nome": "Temperatura",
        "tempMax": 40,
        "tempMin": 10,
        "tipo": "SensoreTemperatura",
        "unitaMisura": "°",
        "valore": 29.59,
        "valoreTarget": 20
    },
    {
        "gruppo": "UmiditàTarget 15",
        "icona": "C:/Users/samsung/Desktop/PAO grafica/untitled/img/goccia.png",
        "id": 2,
        "nome": "Umidità",
        "tipo": "SensoreUmidita",
        "unitaMisura": "%",
        "valore": 12.74,
        "valoreTarget": 15
    },
    {
        "dimmer": false,
        "gruppo": "10W NO dimm",
        "icona": "C:/Users/samsung/Desktop/PAO grafica/untitled/img/lampadina.png",
        "id": 3,
        "nome": "Lampadina",
        "potenzaMax": 10,
        "tipo": "SensoreLampadina",
        "unitaMisura": "W",
        "valore": 10
    },
    {
        "dimmer": true,
        "gruppo": "10W SI dimm",
        "icona": "C:/Users/samsung/Desktop/PAO grafica/untitled/img/lampadina.png",
        "id": 4,
        "nome": "Lampadina",
        "potenzaMax": 10,
        "tipo": "SensoreLampadina",
        "unitaMisura": "W",
        "valore": 2
    },
    {
        "gruppo": "10 pannelli da 400W",
        "icona": "C:/Users/samsung/Desktop/PAO grafica/untitled/img/pannello.png",
        "id": 5,
        "nPannelli": 10,
        "nome": "Pannelli",
        "potenzaMax": 4000,
        "potenzaPannello": 400,
        "tipo": "SensorePannelli",
        "unitaMisura": "W",
        "valore": 2766.22
    },
    {
        "classeEnergetica": "B",
        "gruppo": "TV Classe B",
        "icona": "C:/Users/samsung/Desktop/PAO grafica/untitled/img/tv.png",
        "id": 6,
        "nome": "Elettrodomestico",
        "potenzaMax": 300,
        "tipo": "SensoreElettrodomestico",
        "unitaMisura": "W",
        "valore": 83.36
    }
]
